mdtoolbelt/__init__.py
mdtoolbelt/console.py
mdtoolbelt/conversions.py
mdtoolbelt/formats.py
mdtoolbelt/frame_counts.py
mdtoolbelt/gmx_spells.py
mdtoolbelt/mdt_spells.py
mdtoolbelt/pyt_spells.py
mdtoolbelt/selections.py
mdtoolbelt/single_frame_getter.py
mdtoolbelt/structures.py
mdtoolbelt/subsets.py
mdtoolbelt/vmd_spells.py
mdtoolbelt-0.0.4.dist-info/LICENSE
mdtoolbelt-0.0.4.dist-info/METADATA
mdtoolbelt-0.0.4.dist-info/WHEEL
mdtoolbelt-0.0.4.dist-info/entry_points.txt
mdtoolbelt-0.0.4.dist-info/top_level.txt
mdtoolbelt-0.0.4.dist-info/RECORD
