Metadata-Version: 2.1
Name: mdtoolbelt
Version: 0.0.4
Summary: Tools por MD post-processing
Home-page: https://github.com/d-beltran/mdtoolbelt
Author: Dani Beltrán
Author-email: d.beltran.anadon@gmail.com
License: UNKNOWN
Project-URL: Bug Tracker, https://github.com/d-beltran/mdtoolbelt/issues
Platform: UNKNOWN
Classifier: Programming Language :: Python :: 3
Classifier: License :: OSI Approved :: MIT License
Requires-Python: >=3.6
License-File: LICENSE
